[{"symbol": "ADSL", "series": "EQ", "open_price": 145.45, "high_price": 147.5, "low_price": 142.6, "close_price": 144.65, "last_price": 144.7, "prev_close_price": 143.9, "tot_traded_qty": 594542.0, "tot_traded_value": 86149075.9, "timestamp": "2024-05-03", "tot_trads": 8839.0, "isin": "INE102I01027", "day_pnl": 0, "day_pnl_pr": 1.0, "seven_day_return": 5.31, "fifteen_day_return": 5.01, "thirty_day_return": -1.83, "ytd_day_return": 5.01, "sixty_day_return": -5.12, "ninty_day_return": -17.91, "one80_day_return": 27.61, "three60_day_return": 70.28, "trend": "Down Trend"}]