[{"symbol": "AGI", "series": "EQ", "open_price": 768.0, "high_price": 793.4, "low_price": 756.9, "close_price": 770.35, "last_price": 771.0, "prev_close_price": 812.55, "tot_traded_qty": 573738.0, "tot_traded_value": 443357994.8, "timestamp": "2024-05-03", "tot_trads": 33030.0, "isin": "INE415A01038", "day_pnl": -42, "day_pnl_pr": -5.0, "seven_day_return": -9.01, "fifteen_day_return": -4.19, "thirty_day_return": 0.33, "ytd_day_return": -8.77, "sixty_day_return": -12.81, "ninty_day_return": -1.38, "one80_day_return": -14.43, "three60_day_return": 55.28, "trend": "Down Trend"}]