[{"symbol": "APOLLOTYRE", "series": "EQ", "open_price": 479.9, "high_price": 482.95, "low_price": 466.9, "close_price": 480.75, "last_price": 480.95, "prev_close_price": 478.55, "tot_traded_qty": 1246498.0, "tot_traded_value": 594438601.4, "timestamp": "2024-05-10", "tot_trads": 32531.0, "isin": "INE438A01022", "day_pnl": 2, "day_pnl_pr": 0.0, "seven_day_return": -6.35, "fifteen_day_return": 0.15, "thirty_day_return": 2.32, "ytd_day_return": 11.71, "sixty_day_return": -6.96, "ninty_day_return": -13.07, "one80_day_return": 17.17, "three60_day_return": 30.62, "trend": "Down Trend"}]