[{"symbol": "ASHOKA", "series": "EQ", "open_price": 165.95, "high_price": 167.6, "low_price": 162.9, "close_price": 165.95, "last_price": 166.5, "prev_close_price": 166.25, "tot_traded_qty": 653307.0, "tot_traded_value": 107944132.65, "timestamp": "2024-05-13", "tot_trads": 25767.0, "isin": "INE442H01029", "day_pnl": 0, "day_pnl_pr": 1.0, "seven_day_return": -3.38, "fifteen_day_return": -5.6, "thirty_day_return": -3.04, "ytd_day_return": 21.13, "sixty_day_return": 0.91, "ninty_day_return": -5.58, "one80_day_return": 16.91, "three60_day_return": 94.78, "trend": "Down Trend"}]