[{"symbol": "ATUL", "series": "EQ", "open_price": 5925.0, "high_price": 6037.95, "low_price": 5893.7, "close_price": 5960.35, "last_price": 5960.0, "prev_close_price": 5929.4, "tot_traded_qty": 65292.0, "tot_traded_value": 390167276.2, "timestamp": "2024-04-29", "tot_trads": 12102.0, "isin": "INE100A01010", "day_pnl": 30, "day_pnl_pr": 1.0, "seven_day_return": 1.16, "fifteen_day_return": -3.16, "thirty_day_return": null, "ytd_day_return": -15.23, "sixty_day_return": -5.2, "ninty_day_return": -5.08, "one80_day_return": -2.87, "three60_day_return": -9.58, "trend": "Down Trend"}]