[{"symbol": "BASF", "series": "EQ", "open_price": 4360.0, "high_price": 4388.95, "low_price": 4213.25, "close_price": 4289.65, "last_price": 4287.0, "prev_close_price": 4362.9, "tot_traded_qty": 33653.0, "tot_traded_value": 145224218.65, "timestamp": "2024-05-30", "tot_trads": 5484.0, "isin": "INE373A01013", "day_pnl": -73, "day_pnl_pr": -2.0, "seven_day_return": -6.23, "fifteen_day_return": -6.23, "thirty_day_return": 14.8, "ytd_day_return": 14.8, "sixty_day_return": 20.79, "ninty_day_return": 29.38, "one80_day_return": 44.65, "three60_day_return": 70.26, "trend": "Down Trend"}]