[{"symbol": "BAYERCROP", "series": "EQ", "open_price": 5381.4, "high_price": 5474.85, "low_price": 5305.55, "close_price": 5403.7, "last_price": 5425.0, "prev_close_price": 5392.35, "tot_traded_qty": 8832.0, "tot_traded_value": 47449931.5, "timestamp": "2024-05-08", "tot_trads": 3843.0, "isin": "INE462A01022", "day_pnl": 11, "day_pnl_pr": 0.0, "seven_day_return": -1.31, "fifteen_day_return": -4.29, "thirty_day_return": 0.16, "ytd_day_return": -5.39, "sixty_day_return": -2.14, "ninty_day_return": -5.5, "one80_day_return": 3.07, "three60_day_return": 29.46, "trend": "Down Trend"}]