[{"symbol": "BBTCL", "series": "EQ", "open_price": 265.0, "high_price": 266.0, "low_price": 258.75, "close_price": 262.55, "last_price": 262.85, "prev_close_price": 261.9, "tot_traded_qty": 3139.0, "tot_traded_value": 822462.6, "timestamp": "2024-04-29", "tot_trads": 180.0, "isin": "INE01EE01011", "day_pnl": 0, "day_pnl_pr": 0.0, "seven_day_return": 0.13, "fifteen_day_return": -2.03, "thirty_day_return": null, "ytd_day_return": 2.36, "sixty_day_return": -5.2, "ninty_day_return": -1.67, "one80_day_return": 8.4, "three60_day_return": 12.56, "trend": "Down Trend"}]