[{"symbol": "CAMPUS", "series": "EQ", "open_price": 252.25, "high_price": 255.8, "low_price": 250.0, "close_price": 250.75, "last_price": 251.55, "prev_close_price": 247.35, "tot_traded_qty": 774647.0, "tot_traded_value": 195416771.85, "timestamp": "2024-05-02", "tot_trads": 17699.0, "isin": "INE278Y01022", "day_pnl": 3, "day_pnl_pr": 1.0, "seven_day_return": 6.03, "fifteen_day_return": 9.0, "thirty_day_return": 10.51, "ytd_day_return": -10.01, "sixty_day_return": 2.41, "ninty_day_return": -6.97, "one80_day_return": -6.16, "three60_day_return": -30.26, "trend": "Down Trend"}]