[{"symbol": "CANTABIL", "series": "EQ", "open_price": 214.0, "high_price": 216.9, "low_price": 213.0, "close_price": 213.45, "last_price": 213.0, "prev_close_price": 213.1, "tot_traded_qty": 68842.0, "tot_traded_value": 14730040.25, "timestamp": "2024-04-30", "tot_trads": 2587.0, "isin": "INE068L01024", "day_pnl": 0, "day_pnl_pr": 0.0, "seven_day_return": -0.02, "fifteen_day_return": 1.19, "thirty_day_return": null, "ytd_day_return": -10.84, "sixty_day_return": -7.64, "ninty_day_return": -16.16, "one80_day_return": -81.13, "three60_day_return": -78.94, "trend": "Down Trend"}]