[{"symbol": "COFFEEDAY", "series": "EQ", "open_price": 54.7, "high_price": 56.1, "low_price": 54.35, "close_price": 55.2, "last_price": 55.8, "prev_close_price": 54.7, "tot_traded_qty": 1819585.0, "tot_traded_value": 100765083.9, "timestamp": "2024-05-29", "tot_trads": 6040.0, "isin": "INE335K01011", "day_pnl": 0, "day_pnl_pr": 2.0, "seven_day_return": -8.99, "fifteen_day_return": -8.99, "thirty_day_return": -11.18, "ytd_day_return": -11.18, "sixty_day_return": 2.7, "ninty_day_return": -2.82, "one80_day_return": 20.66, "three60_day_return": 48.59, "trend": "Down Trend"}]