[{"symbol": "DEVIT", "series": "EQ", "open_price": 118.35, "high_price": 118.35, "low_price": 114.1, "close_price": 114.95, "last_price": 115.5, "prev_close_price": 117.05, "tot_traded_qty": 11064.0, "tot_traded_value": 1279462.8, "timestamp": "2024-05-03", "tot_trads": 379.0, "isin": "INE060X01026", "day_pnl": -2, "day_pnl_pr": -2.0, "seven_day_return": -5.23, "fifteen_day_return": -2.83, "thirty_day_return": 3.84, "ytd_day_return": -32.08, "sixty_day_return": -13.57, "ninty_day_return": -28.16, "one80_day_return": -13.83, "three60_day_return": 18.32, "trend": "Down Trend"}]