[{"symbol": "EIFFL", "series": "EQ", "open_price": 133.35, "high_price": 136.45, "low_price": 131.0, "close_price": 133.25, "last_price": 133.0, "prev_close_price": 133.55, "tot_traded_qty": 18360.0, "tot_traded_value": 2462187.7, "timestamp": "2024-05-03", "tot_trads": 163.0, "isin": "INE546V01010", "day_pnl": 0, "day_pnl_pr": 1.0, "seven_day_return": -2.13, "fifteen_day_return": 0.76, "thirty_day_return": -2.09, "ytd_day_return": -9.26, "sixty_day_return": -2.74, "ninty_day_return": -6.36, "one80_day_return": -5.7, "three60_day_return": -11.7, "trend": "Down Trend"}]