[{"symbol": "ELIN", "series": "EQ", "open_price": 163.15, "high_price": 164.95, "low_price": 158.55, "close_price": 160.9, "last_price": 159.25, "prev_close_price": 163.05, "tot_traded_qty": 152502.0, "tot_traded_value": 24617280.1, "timestamp": "2024-05-07", "tot_trads": 6917.0, "isin": "INE050401020", "day_pnl": -2, "day_pnl_pr": -1.0, "seven_day_return": -3.01, "fifteen_day_return": -6.02, "thirty_day_return": null, "ytd_day_return": 8.64, "sixty_day_return": 5.54, "ninty_day_return": 0.75, "one80_day_return": -5.93, "three60_day_return": 22.82, "trend": "Down Trend"}]