[{"symbol": "FMGOETZE", "series": "EQ", "open_price": 381.5, "high_price": 405.0, "low_price": 380.4, "close_price": 384.9, "last_price": 383.0, "prev_close_price": 369.25, "tot_traded_qty": 828601.0, "tot_traded_value": 325575740.15, "timestamp": "2024-05-30", "tot_trads": 34413.0, "isin": "INE529A01010", "day_pnl": 15, "day_pnl_pr": 4.0, "seven_day_return": 5.25, "fifteen_day_return": 5.25, "thirty_day_return": 5.41, "ytd_day_return": 5.41, "sixty_day_return": 13.67, "ninty_day_return": 7.91, "one80_day_return": -1.35, "three60_day_return": 16.85, "trend": "Down Trend"}]