[{"symbol": "FOODSIN", "series": "EQ", "open_price": 151.65, "high_price": 152.0, "low_price": 146.0, "close_price": 148.0, "last_price": 149.5, "prev_close_price": 150.7, "tot_traded_qty": 388501.0, "tot_traded_value": 57748283.65, "timestamp": "2024-05-17", "tot_trads": 3894.0, "isin": "INE976E01023", "day_pnl": -2, "day_pnl_pr": -1.0, "seven_day_return": -0.67, "fifteen_day_return": -8.33, "thirty_day_return": -10.11, "ytd_day_return": -9.06, "sixty_day_return": 5.45, "ninty_day_return": 5.0, "one80_day_return": -17.8, "three60_day_return": -5.73, "trend": "Down Trend"}]