[{"symbol": "GANESHBE", "series": "EQ", "open_price": 150.25, "high_price": 152.7, "low_price": 148.0, "close_price": 149.15, "last_price": 148.85, "prev_close_price": 156.15, "tot_traded_qty": 465151.0, "tot_traded_value": 69794435.45, "timestamp": "2024-05-13", "tot_trads": 10231.0, "isin": "INE388A01029", "day_pnl": -7, "day_pnl_pr": -4.0, "seven_day_return": -7.82, "fifteen_day_return": -12.08, "thirty_day_return": -14.45, "ytd_day_return": -7.7, "sixty_day_return": -21.38, "ninty_day_return": -23.96, "one80_day_return": 1.39, "three60_day_return": 0.0, "trend": "Down Trend"}]