[{"symbol": "GPPL", "series": "EQ", "open_price": 215.95, "high_price": 223.8, "low_price": 215.45, "close_price": 217.55, "last_price": 218.4, "prev_close_price": 214.3, "tot_traded_qty": 4216656.0, "tot_traded_value": 922984903.35, "timestamp": "2024-04-29", "tot_trads": 36538.0, "isin": "INE517F01014", "day_pnl": 3, "day_pnl_pr": 1.0, "seven_day_return": 7.04, "fifteen_day_return": 0.83, "thirty_day_return": null, "ytd_day_return": 46.3, "sixty_day_return": 6.85, "ninty_day_return": 29.22, "one80_day_return": 79.79, "three60_day_return": 94.07, "trend": "Down Trend"}]