[{"symbol": "GTPL", "series": "EQ", "open_price": 183.05, "high_price": 183.05, "low_price": 173.7, "close_price": 175.05, "last_price": 174.25, "prev_close_price": 182.6, "tot_traded_qty": 123767.0, "tot_traded_value": 22179035.05, "timestamp": "2024-05-06", "tot_trads": 4137.0, "isin": "INE869I01013", "day_pnl": -7, "day_pnl_pr": -4.0, "seven_day_return": -1.49, "fifteen_day_return": -5.17, "thirty_day_return": -2.18, "ytd_day_return": -8.61, "sixty_day_return": -8.59, "ninty_day_return": -6.06, "one80_day_return": -3.82, "three60_day_return": 65.06, "trend": "Down Trend"}]