[{"symbol": "HDFCLIFE", "series": "EQ", "open_price": 542.8, "high_price": 553.8, "low_price": 539.55, "close_price": 548.55, "last_price": 549.35, "prev_close_price": 539.55, "tot_traded_qty": 7524779.0, "tot_traded_value": 4130642587.9, "timestamp": "2024-05-10", "tot_trads": 125698.0, "isin": "INE795G01014", "day_pnl": 9, "day_pnl_pr": 2.0, "seven_day_return": -4.82, "fifteen_day_return": -9.47, "thirty_day_return": -13.47, "ytd_day_return": -14.02, "sixty_day_return": -11.8, "ninty_day_return": -7.46, "one80_day_return": -11.35, "three60_day_return": -2.16, "trend": "Down Trend"}]