[{"symbol": "IIFLSEC", "series": "EQ", "open_price": 195.4, "high_price": 196.45, "low_price": 190.0, "close_price": 193.95, "last_price": 193.5, "prev_close_price": 193.0, "tot_traded_qty": 1337648.0, "tot_traded_value": 258984599.75, "timestamp": "2024-05-29", "tot_trads": 18133.0, "isin": "INE489L01022", "day_pnl": 0, "day_pnl_pr": 1.0, "seven_day_return": 31.63, "fifteen_day_return": 31.63, "thirty_day_return": 35.82, "ytd_day_return": 35.82, "sixty_day_return": 50.76, "ninty_day_return": 26.89, "one80_day_return": 67.7, "three60_day_return": 215.37, "trend": "Down Trend"}]