[{"symbol": "IOLCP", "series": "EQ", "open_price": 371.85, "high_price": 373.95, "low_price": 369.35, "close_price": 370.1, "last_price": 370.1, "prev_close_price": 371.85, "tot_traded_qty": 109221.0, "tot_traded_value": 40542617.9, "timestamp": "2024-05-22", "tot_trads": 5207.0, "isin": "INE485C01011", "day_pnl": -1, "day_pnl_pr": -0.0, "seven_day_return": -0.91, "fifteen_day_return": -4.31, "thirty_day_return": -5.03, "ytd_day_return": -21.41, "sixty_day_return": -8.27, "ninty_day_return": -13.94, "one80_day_return": -11.87, "three60_day_return": -15.35, "trend": "Down Trend"}]