[{"symbol": "JTLIND", "series": "EQ", "open_price": 220.0, "high_price": 223.3, "low_price": 217.5, "close_price": 220.5, "last_price": 219.3, "prev_close_price": 220.0, "tot_traded_qty": 2641868.0, "tot_traded_value": 580255815.55, "timestamp": "2024-05-15", "tot_trads": 21020.0, "isin": "INE391J01024", "day_pnl": 0, "day_pnl_pr": 0.0, "seven_day_return": -6.25, "fifteen_day_return": -3.9, "thirty_day_return": 6.75, "ytd_day_return": -7.26, "sixty_day_return": 25.89, "ninty_day_return": -11.62, "one80_day_return": 1.94, "three60_day_return": -28.4, "trend": "Down Trend"}]