[{"symbol": "JUBLINDS", "series": "EQ", "open_price": 1061.0, "high_price": 1125.0, "low_price": 1028.45, "close_price": 1109.05, "last_price": 1122.1, "prev_close_price": 1082.55, "tot_traded_qty": 21636.0, "tot_traded_value": 22657787.75, "timestamp": "2024-05-08", "tot_trads": 1355.0, "isin": "INE645L01011", "day_pnl": 26, "day_pnl_pr": 2.0, "seven_day_return": -4.99, "fifteen_day_return": -4.89, "thirty_day_return": -10.91, "ytd_day_return": 84.27, "sixty_day_return": -20.0, "ninty_day_return": 81.69, "one80_day_return": 81.8, "three60_day_return": 157.71, "trend": "Down Trend"}]