[{"symbol": "LUPIN", "series": "EQ", "open_price": 1614.95, "high_price": 1698.0, "low_price": 1604.0, "close_price": 1688.6, "last_price": 1684.0, "prev_close_price": 1608.55, "tot_traded_qty": 2246490.0, "tot_traded_value": 3722559027.35, "timestamp": "2024-05-13", "tot_trads": 97529.0, "isin": "INE326A01037", "day_pnl": 80, "day_pnl_pr": 5.0, "seven_day_return": 0.53, "fifteen_day_return": 5.91, "thirty_day_return": 4.09, "ytd_day_return": 26.02, "sixty_day_return": 0.71, "ninty_day_return": 4.1, "one80_day_return": 43.22, "three60_day_return": 114.49, "trend": "Down Trend"}]