[{"symbol": "MARALOVER", "series": "EQ", "open_price": 76.8, "high_price": 76.8, "low_price": 72.55, "close_price": 73.1, "last_price": 72.95, "prev_close_price": 74.5, "tot_traded_qty": 20728.0, "tot_traded_value": 1538700.5, "timestamp": "2024-05-21", "tot_trads": 711.0, "isin": "INE882A01013", "day_pnl": -1, "day_pnl_pr": -1.0, "seven_day_return": -0.54, "fifteen_day_return": -5.06, "thirty_day_return": null, "ytd_day_return": 5.94, "sixty_day_return": 14.58, "ninty_day_return": -13.13, "one80_day_return": -0.54, "three60_day_return": 40.44, "trend": "Down Trend"}]