[{"symbol": "MHRIL", "series": "EQ", "open_price": 403.6, "high_price": 418.0, "low_price": 400.0, "close_price": 416.0, "last_price": 416.0, "prev_close_price": 403.65, "tot_traded_qty": 212126.0, "tot_traded_value": 87634179.85, "timestamp": "2024-05-08", "tot_trads": 11211.0, "isin": "INE998I01010", "day_pnl": 12, "day_pnl_pr": 3.0, "seven_day_return": -4.08, "fifteen_day_return": 3.64, "thirty_day_return": 2.37, "ytd_day_return": 10.7, "sixty_day_return": 1.79, "ninty_day_return": -4.26, "one80_day_return": 4.08, "three60_day_return": 41.38, "trend": "Down Trend"}]