[{"symbol": "MONTECARLO", "series": "EQ", "open_price": 622.35, "high_price": 638.0, "low_price": 601.0, "close_price": 616.15, "last_price": 625.0, "prev_close_price": 681.2, "tot_traded_qty": 217250.0, "tot_traded_value": 133301798.95, "timestamp": "2024-05-29", "tot_trads": 14208.0, "isin": "INE950M01013", "day_pnl": -65, "day_pnl_pr": -10.0, "seven_day_return": -10.72, "fifteen_day_return": -10.72, "thirty_day_return": -9.72, "ytd_day_return": -9.72, "sixty_day_return": -2.42, "ninty_day_return": 0.2, "one80_day_return": -11.76, "three60_day_return": -21.95, "trend": "Down Trend"}]