[{"symbol": "MUKTAARTS", "series": "EQ", "open_price": 72.65, "high_price": 74.95, "low_price": 72.65, "close_price": 73.0, "last_price": 73.35, "prev_close_price": 73.95, "tot_traded_qty": 5852.0, "tot_traded_value": 428338.3, "timestamp": "2024-04-29", "tot_trads": 88.0, "isin": "INE374B01019", "day_pnl": 0, "day_pnl_pr": 1.0, "seven_day_return": null, "fifteen_day_return": null, "thirty_day_return": null, "ytd_day_return": null, "sixty_day_return": null, "ninty_day_return": null, "one80_day_return": null, "three60_day_return": 35.06, "trend": "Down Trend"}]