[{"symbol": "NUCLEUS", "series": "EQ", "open_price": 1384.0, "high_price": 1391.3, "low_price": 1340.0, "close_price": 1343.7, "last_price": 1348.9, "prev_close_price": 1381.3, "tot_traded_qty": 22392.0, "tot_traded_value": 30364328.6, "timestamp": "2024-05-06", "tot_trads": 4083.0, "isin": "INE096B01018", "day_pnl": -37, "day_pnl_pr": -3.0, "seven_day_return": -5.63, "fifteen_day_return": 2.76, "thirty_day_return": -2.3, "ytd_day_return": null, "sixty_day_return": -4.02, "ninty_day_return": null, "one80_day_return": null, "three60_day_return": 119.45, "trend": "Down Trend"}]