[{"symbol": "PRESTIGE", "series": "EQ", "open_price": 1534.6, "high_price": 1600.4, "low_price": 1496.9, "close_price": 1505.1, "last_price": 1505.0, "prev_close_price": 1552.05, "tot_traded_qty": 1570831.0, "tot_traded_value": 2427496085.15, "timestamp": "2024-05-29", "tot_trads": 70497.0, "isin": "INE811K01011", "day_pnl": -46, "day_pnl_pr": -3.0, "seven_day_return": 0.99, "fifteen_day_return": 0.99, "thirty_day_return": 13.42, "ytd_day_return": 13.42, "sixty_day_return": 18.79, "ninty_day_return": 28.92, "one80_day_return": 45.03, "three60_day_return": 192.31, "trend": "Down Trend"}]