[{"symbol": "PTL", "series": "EQ", "open_price": 43.45, "high_price": 45.0, "low_price": 43.3, "close_price": 43.65, "last_price": 43.55, "prev_close_price": 43.0, "tot_traded_qty": 233270.0, "tot_traded_value": 10294488.95, "timestamp": "2024-05-08", "tot_trads": 2504.0, "isin": "INE034D01049", "day_pnl": 0, "day_pnl_pr": 2.0, "seven_day_return": 3.07, "fifteen_day_return": 3.68, "thirty_day_return": 3.56, "ytd_day_return": 4.3, "sixty_day_return": -0.68, "ninty_day_return": -15.98, "one80_day_return": 4.05, "three60_day_return": 32.27, "trend": "Down Trend"}]