[{"symbol": "RALLIS", "series": "EQ", "open_price": 271.9, "high_price": 273.3, "low_price": 266.9, "close_price": 268.95, "last_price": 268.7, "prev_close_price": 271.9, "tot_traded_qty": 415177.0, "tot_traded_value": 111994545.65, "timestamp": "2024-05-22", "tot_trads": 14288.0, "isin": "INE613A01020", "day_pnl": -2, "day_pnl_pr": -1.0, "seven_day_return": 2.3, "fifteen_day_return": -1.56, "thirty_day_return": -4.78, "ytd_day_return": 5.82, "sixty_day_return": 7.02, "ninty_day_return": 8.89, "one80_day_return": 24.54, "three60_day_return": 41.22, "trend": "Down Trend"}]