[{"symbol": "RAYMOND", "series": "EQ", "open_price": 2150.0, "high_price": 2151.6, "low_price": 2082.0, "close_price": 2094.65, "last_price": 2094.9, "prev_close_price": 2149.95, "tot_traded_qty": 152997.0, "tot_traded_value": 321802046.65, "timestamp": "2024-05-13", "tot_trads": 17643.0, "isin": "INE301A01014", "day_pnl": -55, "day_pnl_pr": -3.0, "seven_day_return": -4.44, "fifteen_day_return": -1.21, "thirty_day_return": 9.93, "ytd_day_return": 22.97, "sixty_day_return": 23.51, "ninty_day_return": 22.07, "one80_day_return": 10.18, "three60_day_return": 30.85, "trend": "Down Trend"}]