[{"symbol": "RESPONIND", "series": "EQ", "open_price": 294.4, "high_price": 297.75, "low_price": 288.15, "close_price": 291.0, "last_price": 291.4, "prev_close_price": 295.5, "tot_traded_qty": 147154.0, "tot_traded_value": 43472766.05, "timestamp": "2024-05-07", "tot_trads": 3302.0, "isin": "INE688D01026", "day_pnl": -4, "day_pnl_pr": -1.0, "seven_day_return": -3.03, "fifteen_day_return": 1.84, "thirty_day_return": null, "ytd_day_return": -7.24, "sixty_day_return": -2.92, "ninty_day_return": -7.12, "one80_day_return": -12.76, "three60_day_return": 86.06, "trend": "Down Trend"}]