[{"symbol": "RICOAUTO", "series": "EQ", "open_price": 122.8, "high_price": 124.5, "low_price": 121.5, "close_price": 122.9, "last_price": 123.6, "prev_close_price": 122.85, "tot_traded_qty": 769263.0, "tot_traded_value": 94648831.85, "timestamp": "2024-05-29", "tot_trads": 8063.0, "isin": "INE209B01025", "day_pnl": 0, "day_pnl_pr": 1.0, "seven_day_return": -7.18, "fifteen_day_return": -7.18, "thirty_day_return": -13.42, "ytd_day_return": -13.42, "sixty_day_return": -13.48, "ninty_day_return": -0.81, "one80_day_return": 31.87, "three60_day_return": 38.79, "trend": "Down Trend"}]