[{"symbol": "RPSGVENT", "series": "EQ", "open_price": 730.0, "high_price": 734.95, "low_price": 718.4, "close_price": 721.35, "last_price": 718.45, "prev_close_price": 729.25, "tot_traded_qty": 33180.0, "tot_traded_value": 24143067.75, "timestamp": "2024-04-30", "tot_trads": 3535.0, "isin": "INE425Y01011", "day_pnl": -7, "day_pnl_pr": -1.0, "seven_day_return": 2.58, "fifteen_day_return": 4.6, "thirty_day_return": null, "ytd_day_return": -3.34, "sixty_day_return": 1.64, "ninty_day_return": -6.32, "one80_day_return": 34.72, "three60_day_return": 76.13, "trend": "Down Trend"}]