[{"symbol": "SHREEPUSHK", "series": "EQ", "open_price": 174.05, "high_price": 177.2, "low_price": 173.05, "close_price": 175.1, "last_price": 175.0, "prev_close_price": 175.2, "tot_traded_qty": 30825.0, "tot_traded_value": 5397545.55, "timestamp": "2024-05-30", "tot_trads": 1463.0, "isin": "INE712K01011", "day_pnl": 0, "day_pnl_pr": 1.0, "seven_day_return": 1.65, "fifteen_day_return": 1.65, "thirty_day_return": -2.96, "ytd_day_return": -2.96, "sixty_day_return": 1.92, "ninty_day_return": -5.3, "one80_day_return": -8.99, "three60_day_return": -13.38, "trend": "Down Trend"}]