[{"symbol": "SILLYMONKS", "series": "EQ", "open_price": 16.95, "high_price": 19.0, "low_price": 16.5, "close_price": 18.65, "last_price": 17.9, "prev_close_price": 17.3, "tot_traded_qty": 82125.0, "tot_traded_value": 1523441.25, "timestamp": "2024-05-02", "tot_trads": 179.0, "isin": "INE203Y01012", "day_pnl": 1, "day_pnl_pr": 6.0, "seven_day_return": 15.84, "fifteen_day_return": 19.55, "thirty_day_return": 34.17, "ytd_day_return": null, "sixty_day_return": 8.43, "ninty_day_return": -10.77, "one80_day_return": 15.48, "three60_day_return": -14.45, "trend": "Down Trend"}]