[{"symbol": "SOUTHWEST", "series": "EQ", "open_price": 104.55, "high_price": 106.1, "low_price": 102.0, "close_price": 102.65, "last_price": 102.95, "prev_close_price": 106.1, "tot_traded_qty": 48844.0, "tot_traded_value": 5067523.6, "timestamp": "2024-05-30", "tot_trads": 658.0, "isin": "INE980Y01015", "day_pnl": -3, "day_pnl_pr": -3.0, "seven_day_return": -7.44, "fifteen_day_return": -7.44, "thirty_day_return": -13.88, "ytd_day_return": -13.88, "sixty_day_return": -6.13, "ninty_day_return": -20.3, "one80_day_return": -39.78, "three60_day_return": -21.55, "trend": "Down Trend"}]