[{"symbol": "SRF", "series": "EQ", "open_price": 2231.0, "high_price": 2242.75, "low_price": 2214.05, "close_price": 2223.1, "last_price": 2227.8, "prev_close_price": 2239.0, "tot_traded_qty": 372713.0, "tot_traded_value": 829916442.3, "timestamp": "2024-05-30", "tot_trads": 29402.0, "isin": "INE647A01010", "day_pnl": -15, "day_pnl_pr": -1.0, "seven_day_return": -2.85, "fifteen_day_return": -2.85, "thirty_day_return": -15.18, "ytd_day_return": -15.18, "sixty_day_return": -15.04, "ninty_day_return": -7.27, "one80_day_return": -8.42, "three60_day_return": -12.21, "trend": "Down Trend"}]