[{"symbol": "SUNDRMFAST", "series": "EQ", "open_price": 1180.0, "high_price": 1190.0, "low_price": 1165.05, "close_price": 1182.8, "last_price": 1187.0, "prev_close_price": 1179.2, "tot_traded_qty": 34414.0, "tot_traded_value": 40560675.9, "timestamp": "2024-05-22", "tot_trads": 6833.0, "isin": "INE387A01021", "day_pnl": 3, "day_pnl_pr": 0.0, "seven_day_return": 4.23, "fifteen_day_return": 2.83, "thirty_day_return": 10.77, "ytd_day_return": -5.01, "sixty_day_return": 14.57, "ninty_day_return": 7.24, "one80_day_return": -3.86, "three60_day_return": 10.34, "trend": "Down Trend"}]