[{"symbol": "SUPREMEIND", "series": "EQ", "open_price": 4978.85, "high_price": 5299.95, "low_price": 4928.55, "close_price": 5273.15, "last_price": 5260.0, "prev_close_price": 4957.55, "tot_traded_qty": 796893.0, "tot_traded_value": 4110288740.8, "timestamp": "2024-05-06", "tot_trads": 82986.0, "isin": "INE195A01028", "day_pnl": 315, "day_pnl_pr": 6.0, "seven_day_return": 6.42, "fifteen_day_return": 25.59, "thirty_day_return": 21.05, "ytd_day_return": 13.97, "sixty_day_return": 30.28, "ninty_day_return": 27.44, "one80_day_return": 19.83, "three60_day_return": 89.31, "trend": "Down Trend"}]