[{"symbol": "SURYALAXMI", "series": "EQ", "open_price": 73.25, "high_price": 78.95, "low_price": 72.7, "close_price": 75.35, "last_price": 74.7, "prev_close_price": 72.05, "tot_traded_qty": 83942.0, "tot_traded_value": 6389416.8, "timestamp": "2024-04-30", "tot_trads": 1262.0, "isin": "INE713B01026", "day_pnl": 3, "day_pnl_pr": 4.0, "seven_day_return": 6.05, "fifteen_day_return": 4.58, "thirty_day_return": null, "ytd_day_return": -5.58, "sixty_day_return": -3.52, "ninty_day_return": -2.96, "one80_day_return": 23.73, "three60_day_return": 42.17, "trend": "Down Trend"}]