[{"symbol": "TATAPOWER", "series": "EQ", "open_price": 435.0, "high_price": 439.45, "low_price": 432.1, "close_price": 432.85, "last_price": 433.5, "prev_close_price": 436.9, "tot_traded_qty": 7241846.0, "tot_traded_value": 3149268514.95, "timestamp": "2024-05-29", "tot_trads": 83642.0, "isin": "INE245A01021", "day_pnl": -4, "day_pnl_pr": -1.0, "seven_day_return": 0.58, "fifteen_day_return": 0.58, "thirty_day_return": -3.38, "ytd_day_return": -3.38, "sixty_day_return": 6.36, "ninty_day_return": 14.69, "one80_day_return": 56.83, "three60_day_return": 97.6, "trend": "Down Trend"}]