[{"symbol": "TECHM", "series": "EQ", "open_price": 1330.0, "high_price": 1335.4, "low_price": 1311.05, "close_price": 1330.4, "last_price": 1330.1, "prev_close_price": 1323.9, "tot_traded_qty": 1411627.0, "tot_traded_value": 1873821763.9, "timestamp": "2024-05-22", "tot_trads": 74037.0, "isin": "INE669C01036", "day_pnl": 6, "day_pnl_pr": 0.0, "seven_day_return": 5.42, "fifteen_day_return": 5.4, "thirty_day_return": 10.13, "ytd_day_return": 3.93, "sixty_day_return": 6.24, "ninty_day_return": 1.56, "one80_day_return": 9.79, "three60_day_return": 21.15, "trend": "Down Trend"}]