[{"symbol": "TRIVENI", "series": "EQ", "open_price": 364.0, "high_price": 367.95, "low_price": 359.05, "close_price": 363.45, "last_price": 364.0, "prev_close_price": 362.35, "tot_traded_qty": 404468.0, "tot_traded_value": 147177194.55, "timestamp": "2024-05-02", "tot_trads": 16334.0, "isin": "INE256C01024", "day_pnl": 1, "day_pnl_pr": 0.0, "seven_day_return": 2.38, "fifteen_day_return": 12.16, "thirty_day_return": 9.67, "ytd_day_return": 8.02, "sixty_day_return": 12.73, "ninty_day_return": 7.86, "one80_day_return": 2.86, "three60_day_return": 30.13, "trend": "Down Trend"}]