[{"symbol": "TVSSRICHAK", "series": "EQ", "open_price": 4200.0, "high_price": 4200.0, "low_price": 4130.0, "close_price": 4172.9, "last_price": 4195.0, "prev_close_price": 4188.55, "tot_traded_qty": 4453.0, "tot_traded_value": 18528110.75, "timestamp": "2024-05-03", "tot_trads": 1184.0, "isin": "INE421C01016", "day_pnl": -15, "day_pnl_pr": -0.0, "seven_day_return": 0.99, "fifteen_day_return": -4.58, "thirty_day_return": 5.78, "ytd_day_return": -10.31, "sixty_day_return": -4.51, "ninty_day_return": -4.8, "one80_day_return": 6.11, "three60_day_return": 32.38, "trend": "Down Trend"}]