[{"symbol": "UNOMINDA", "series": "EQ", "open_price": 766.45, "high_price": 774.4, "low_price": 750.0, "close_price": 757.75, "last_price": 760.0, "prev_close_price": 759.45, "tot_traded_qty": 277019.0, "tot_traded_value": 210096899.65, "timestamp": "2024-05-22", "tot_trads": 23422.0, "isin": "INE405E01023", "day_pnl": -1, "day_pnl_pr": -0.0, "seven_day_return": 3.67, "fifteen_day_return": 3.43, "thirty_day_return": 4.39, "ytd_day_return": 12.71, "sixty_day_return": 19.86, "ninty_day_return": 17.25, "one80_day_return": 17.8, "three60_day_return": 39.75, "trend": "Down Trend"}]