[{"symbol": "VAISHALI", "series": "EQ", "open_price": 145.45, "high_price": 146.6, "low_price": 142.6, "close_price": 143.55, "last_price": 142.95, "prev_close_price": 145.45, "tot_traded_qty": 16599.0, "tot_traded_value": 2394499.7, "timestamp": "2024-05-29", "tot_trads": 445.0, "isin": "INE972X01014", "day_pnl": -1, "day_pnl_pr": -1.0, "seven_day_return": -12.5, "fifteen_day_return": -12.5, "thirty_day_return": -9.46, "ytd_day_return": -9.46, "sixty_day_return": -0.9, "ninty_day_return": -2.55, "one80_day_return": 1.59, "three60_day_return": 10.98, "trend": "Down Trend"}]