[{"symbol": "VINNY", "series": "EQ", "open_price": 4.4, "high_price": 4.6, "low_price": 4.35, "close_price": 4.6, "last_price": 4.6, "prev_close_price": 4.4, "tot_traded_qty": 512187.0, "tot_traded_value": 2312230.1, "timestamp": "2024-05-08", "tot_trads": 974.0, "isin": "INE01KI01027", "day_pnl": 0, "day_pnl_pr": 25.0, "seven_day_return": 9.52, "fifteen_day_return": 12.2, "thirty_day_return": null, "ytd_day_return": null, "sixty_day_return": null, "ninty_day_return": null, "one80_day_return": null, "three60_day_return": null, "trend": "Down Trend"}]