[{"symbol": "WIPRO", "series": "EQ", "open_price": 463.0, "high_price": 464.8, "low_price": 459.7, "close_price": 460.9, "last_price": 460.6, "prev_close_price": 462.55, "tot_traded_qty": 4233724.0, "tot_traded_value": 1955615977.05, "timestamp": "2024-05-21", "tot_trads": 91428.0, "isin": "INE075A01022", "day_pnl": -1, "day_pnl_pr": -0.0, "seven_day_return": 1.98, "fifteen_day_return": 0.78, "thirty_day_return": null, "ytd_day_return": -2.13, "sixty_day_return": -9.66, "ninty_day_return": -14.0, "one80_day_return": 15.17, "three60_day_return": 16.95, "trend": "Down Trend"}]