[{"symbol": "XCHANGING", "series": "EQ", "open_price": 117.7, "high_price": 119.55, "low_price": 116.65, "close_price": 117.1, "last_price": 118.5, "prev_close_price": 117.55, "tot_traded_qty": 113399.0, "tot_traded_value": 13391559.7, "timestamp": "2024-05-08", "tot_trads": 2222.0, "isin": "INE692G01013", "day_pnl": 0, "day_pnl_pr": 1.0, "seven_day_return": -4.17, "fifteen_day_return": -3.3, "thirty_day_return": -11.12, "ytd_day_return": 6.21, "sixty_day_return": -11.09, "ninty_day_return": 0.9, "one80_day_return": 18.16, "three60_day_return": 95.33, "trend": "Down Trend"}]