[{"symbol": "ZENTEC", "series": "EQ", "open_price": 920.5, "high_price": 941.05, "low_price": 916.45, "close_price": 933.2, "last_price": 933.0, "prev_close_price": 925.7, "tot_traded_qty": 230873.0, "tot_traded_value": 214149580.2, "timestamp": "2024-05-29", "tot_trads": 9510.0, "isin": "INE251B01027", "day_pnl": 7, "day_pnl_pr": 1.0, "seven_day_return": -3.07, "fifteen_day_return": -3.07, "thirty_day_return": -12.59, "ytd_day_return": -12.59, "sixty_day_return": -1.31, "ninty_day_return": 2.65, "one80_day_return": 21.01, "three60_day_return": 122.14, "trend": "Down Trend"}]