[{"symbol": "ZENTEC", "series": "EQ", "open_price": 945.1, "high_price": 971.0, "low_price": 933.1, "close_price": 933.1, "last_price": 933.1, "prev_close_price": 982.2, "tot_traded_qty": 1182324.0, "tot_traded_value": 1115782902.35, "timestamp": "2024-05-08", "tot_trads": 31650.0, "isin": "INE251B01027", "day_pnl": -49, "day_pnl_pr": -5.0, "seven_day_return": -12.6, "fifteen_day_return": -8.75, "thirty_day_return": -9.2, "ytd_day_return": 15.18, "sixty_day_return": -0.07, "ninty_day_return": null, "one80_day_return": null, "three60_day_return": 203.55, "trend": "Down Trend"}]